pycimvp/__init__.py
pycimvp/__version__.py
pycimvp/main.py
pycimvp-1.0.3.dist-info/LICENSE
pycimvp-1.0.3.dist-info/METADATA
pycimvp-1.0.3.dist-info/WHEEL
pycimvp-1.0.3.dist-info/top_level.txt
pycimvp-1.0.3.dist-info/RECORD
