Metadata-Version: 2.1
Name: pycimvp
Version: 1.0.3
Summary: A Python library project for TDD + CI.
Home-page: https://pycimvp.readthedocs.io/
Author: Lee Shiueh
License: Apache 2.0
Platform: UNKNOWN
